beeper_desktop_api/__init__.py
beeper_desktop_api/_base_client.py
beeper_desktop_api/_client.py
beeper_desktop_api/_compat.py
beeper_desktop_api/_constants.py
beeper_desktop_api/_exceptions.py
beeper_desktop_api/_files.py
beeper_desktop_api/_models.py
beeper_desktop_api/_qs.py
beeper_desktop_api/_resource.py
beeper_desktop_api/_response.py
beeper_desktop_api/_streaming.py
beeper_desktop_api/_types.py
beeper_desktop_api/_version.py
beeper_desktop_api/pagination.py
beeper_desktop_api/py.typed
beeper_desktop_api/_utils/__init__.py
beeper_desktop_api/_utils/_compat.py
beeper_desktop_api/_utils/_datetime_parse.py
beeper_desktop_api/_utils/_logs.py
beeper_desktop_api/_utils/_proxy.py
beeper_desktop_api/_utils/_reflection.py
beeper_desktop_api/_utils/_resources_proxy.py
beeper_desktop_api/_utils/_streams.py
beeper_desktop_api/_utils/_sync.py
beeper_desktop_api/_utils/_transform.py
beeper_desktop_api/_utils/_typing.py
beeper_desktop_api/_utils/_utils.py
beeper_desktop_api/lib/.keep
beeper_desktop_api/resources/__init__.py
beeper_desktop_api/resources/assets.py
beeper_desktop_api/resources/messages.py
beeper_desktop_api/resources/accounts/__init__.py
beeper_desktop_api/resources/accounts/accounts.py
beeper_desktop_api/resources/accounts/contacts.py
beeper_desktop_api/resources/chats/__init__.py
beeper_desktop_api/resources/chats/chats.py
beeper_desktop_api/resources/chats/reminders.py
beeper_desktop_api/types/__init__.py
beeper_desktop_api/types/account.py
beeper_desktop_api/types/account_list_response.py
beeper_desktop_api/types/asset_download_params.py
beeper_desktop_api/types/asset_download_response.py
beeper_desktop_api/types/chat.py
beeper_desktop_api/types/chat_archive_params.py
beeper_desktop_api/types/chat_create_params.py
beeper_desktop_api/types/chat_create_response.py
beeper_desktop_api/types/chat_list_params.py
beeper_desktop_api/types/chat_list_response.py
beeper_desktop_api/types/chat_retrieve_params.py
beeper_desktop_api/types/chat_search_params.py
beeper_desktop_api-4.1.296.dist-info/METADATA
beeper_desktop_api-4.1.296.dist-info/WHEEL
beeper_desktop_api-4.1.296.dist-info/licenses/LICENSE
beeper_desktop_api-4.1.296.dist-info/RECORD
